LICENSE
MANIFEST.in
README.rst
setup.cfg
setup.py
gjtk/__init__.py
gjtk/__main__.py
gjtk/extract.py
gjtk/generate.py
gjtk/random.py
gjtk/validate.py
gjtk.egg-info/PKG-INFO
gjtk.egg-info/SOURCES.txt
gjtk.egg-info/dependency_links.txt
gjtk.egg-info/entry_points.txt
gjtk.egg-info/requires.txt
gjtk.egg-info/top_level.txt
gjtk/test/__init__.py
gjtk/test/test_extract.py
gjtk/test/test_generate.py
gjtk/test/test_random.py
gjtk/test/test_validate.py
gjtk/test/test_validate_examples.py