Metadata-Version: 1.1
Name: gjtk
Version: 3.0.0
Summary: GeoJSON ToolKit
Home-page: https://github.com/dmtucker/gjtk-py
Author: David Tucker
Author-email: david.michael.tucker@gmail.com
License: LGPLv2+
Keywords: GeoJSON
Platform: UNKNOWN
Classifier: License :: OSI Approved :: GNU Lesser General Public License v2 or later (LGPLv2+)
Classifier: Intended Audience :: Developers
Classifier: Programming Language :: Python :: 2
Classifier: Programming Language :: Python :: 2.7
Classifier: Programming Language :: Python :: 3
Classifier: Programming Language :: Python :: 3.3
Classifier: Programming Language :: Python :: 3.4
Classifier: Programming Language :: Python :: 3.5
Classifier: Topic :: Software Development :: Libraries
Classifier: Development Status :: 4 - Beta
